tree_sitter_m3u-0.0.1.dist-info/RECORD
tree_sitter_m3u-0.0.1.dist-info/WHEEL
tree_sitter_m3u-0.0.1.dist-info/entry_points.txt
tree_sitter_m3u-0.0.1.dist-info/METADATA
tree_sitter_m3u-0.0.1.data/data/lib/parser/m3u.dylib
tree_sitter_m3u/_version.py
tree_sitter_m3u/__init__.py
tree_sitter_m3u/py.typed
tree_sitter_m3u/__main__.py
