Metadata-Version: 2.1
Name: tree-sitter-m3u
Version: 0.0.1
Summary: m3u grammar for tree-sitter
Keywords: parsing incremental
Author-Email: Wu Zhenyu <wuzhenyu@ustc.edu>
License: GPL v3
Classifier: Development Status :: 3 - Alpha
Classifier: Intended Audience :: Developers
Classifier: Topic :: Software Development :: Build Tools
Classifier: License :: OSI Approved :: GNU General Public License v3 (GPLv3)
Classifier: Operating System :: Microsoft :: Windows
Classifier: Operating System :: POSIX
Classifier: Operating System :: Unix
Classifier: Operating System :: MacOS
Classifier: Programming Language :: Python :: 3 :: Only
Classifier: Programming Language :: Python :: 3
Classifier: Programming Language :: Python :: 3.7
Classifier: Programming Language :: Python :: 3.8
Classifier: Programming Language :: Python :: 3.9
Classifier: Programming Language :: Python :: 3.10
Classifier: Programming Language :: Python :: 3.11
Classifier: Programming Language :: Python :: 3.12
Classifier: Programming Language :: Python :: Implementation :: CPython
Classifier: Programming Language :: Python :: Implementation :: PyPy
Project-URL: Homepage, https://tree-sitter-m3u.readthedocs.io
Project-URL: Download, https://github.com/Freed-Wu/tree-sitter-m3u/releases
Project-URL: Bug report, https://github.com/Freed-Wu/tree-sitter-m3u/issues
Project-URL: Source, https://github.com/Freed-Wu/tree-sitter-m3u
Requires-Python: >=3.10
Requires-Dist: tree-sitter
Requires-Dist: pytest-cov; extra == "dev"
Requires-Dist: tree_sitter_lsp; extra == "colorize"
Provides-Extra: dev
Provides-Extra: colorize
